pymdt/__init__.py
pymdt/core.py
pymdt/distributions.py
pymdt/io.py
pymdt/metrics.py
pymdt/missions.py
pymdt/results.py
pymdt/solving.py
pymdt/specs.py
pymdt/utils.py
sandia_pymdt-1.4.2520.dist-info/licenses/LICENSE
sandia_pymdt-1.4.2520.dist-info/METADATA
sandia_pymdt-1.4.2520.dist-info/WHEEL
sandia_pymdt-1.4.2520.dist-info/top_level.txt
sandia_pymdt-1.4.2520.dist-info/RECORD
