Metadata-Version: 2.4
Name: sandia-pymdt
Version: 1.4.2520
Summary: Python Scripting Front-End for the Microgrid Design Toolkit
Author-email: John Eddy <jpeddy@sandia.gov>
License-Expression: BSD-3-Clause
Project-URL: Homepage, https://energy.sandia.gov/programs/electric-grid/advanced-microgrids/microgrid-design-toolkit/
Project-URL: GitHub, https://github.com/sandialabs/pymdt
Classifier: Programming Language :: Python :: 3
Classifier: Operating System :: Microsoft :: Windows
Requires-Python: >=3.9.0
License-File: LICENSE
Requires-Dist: pythonnet>=3.0.3
Dynamic: license-file
